quote_maker/__init__.py
quote_maker/main.py
quote_maker/fonts/Quote.ttf
quote_maker-0.0.1.dist-info/entry_points.txt
quote_maker-0.0.1.dist-info/LICENSE
quote_maker-0.0.1.dist-info/WHEEL
quote_maker-0.0.1.dist-info/METADATA
quote_maker-0.0.1.dist-info/RECORD
