Metadata-Version: 2.1
Name: quote_maker
Version: 0.0.1
Summary: Just another python script to automate boring stuff. Quote maker easy to create a quoted image and publish to a Facebook page.
Home-page: https://github.com/shajeen/Quote-Maker
Author: Sheik S Shajeen Ahamed
Author-email: shajeenahmed@gmail.com
Classifier: License :: OSI Approved :: MIT License
